Workbook

Sheet BS_Input
B1: 2024年年报 | C1: 2023年年报 | D1: 2022年年报 | E1: 2021年年报 | F1: 2020年年报 | G1: 2019年年报 | H1: 2018年年报 | I1: 2017年年报 | J1: 2016年年报
A2: 上市前/上市后 | B2: 上市后 | C2: 上市后 | D2: 上市后 | E2: 上市后 | F2: 上市后 | G2: 上市后 | H2: 上市后 | I2: 上市后 | J2: 上市后
A3: 报表类型 | B3: 合并报表 | C3: 合并报表 | D3: 合并报表 | E3: 合并报表 | F3: 合并报表 | G3: 合并报表 | H3: 合并报表 | I3: 合并报表 | J3: 合并报表
A4: 公司类型 | B4: 通用 | C4: 通用 | D4: 通用 | E4: 通用 | F4: 通用 | G4: 通用 | H4: 通用 | I4: 通用 | J4: 通用
A5: 流动资产：
A6: 货币资金(元) | B6: 1.7230466e+09 | C6: 1.8454782e+09 | D6: 2.0016372e+09 | E6: 1.5263752e+09 | F6: 1.6245794e+09 | G6: 1.2289292e+09 | H6: 5.4171848e+08 | I6: 2.2571957e+08 | J6: 3.6542138e+08
A7: 结算备付金(元)
A8: 拆出资金(元)
A9: 交易性金融资产(元) | B9: 50322385 | C9: 8626
A10: 融出资金(元)
A11: 衍生金融资产(元)
A12: 应收票据及应收账款(元) | B12: 1.0354027e+09 | C12: 8.516872e+08 | D12: 7.9089003e+08 | E12: 5.6701377e+08 | F12: 4.5893045e+08 | G12: 5.9552627e+08 | H12: 6.431564e+08 | I12: 6.4250561e+08 | J12: 6.0638719e+08
A13: 其中：应收票据(元) | B13: 1.6284804e+08 | C13: 1.2649992e+08 | D13: 81735132 | E13: 36878518 | F13: 19848429 | G13: 13031312
A14: 应收账款(元) | B14: 8.7255467e+08 | C14: 7.2518728e+08 | D14: 7.091549e+08 | E14: 5.3013525e+08 | F14: 4.3908202e+08 | G14: 5.8249496e+08
A15: 应收款项融资(元) | B15: 94302276 | C15: 82686082 | D15: 28083359 | E15: 1.1863742e+08 | F15: 1.6519979e+08 | G15: 2.1538344e+08
A16: 预付款项(元) | B16: 21769366 | C16: 1.2868559e+08 | D16: 83408660 | E16: 74100936 | F16: 83035411 | G16: 62875294 | H16: 59595477 | I16: 59776583 | J16: 55734929
A17: 应收保费(元)
A18: 应收分保账款(元)
A19: 应收分保合同准备金(元)
A20: 其他应收款合计(元) | B20: 50452913 | C20: 48718511 | D20: 41120234 | E20: 69568637 | F20: 33382133 | G20: 34837582 | H20: 20475174 | I20: 20424633 | J20: 16430420
A21: 其中：应收利息(元) | G21: 2343561.6
A22: 应收股利(元)
A23: 其他应收款(元) | B23: 50452913 | C23: 48718511 | D23: 41120234 | E23: 69568637 | F23: 33382133 | G23: 32494020 | H23: 20475174 | I23: 20424633 | J23: 16430420
A24: 应收出口退税(元)
A25: 应收补贴款(元)
A26: 内部应收款(元)
A27: 买入返售金融资产(元)
A28: 以摊余成本计量的金融资产(元)
A29: 以公允价值计量且其变动计入其他综合收益的金融资产(元)
A30: 存货(元) | B30: 2.5660182e+09 | C30: 2.8194927e+09 | D30: 2.4595959e+09 | E30: 1.8670697e+09 | F30: 1.60389e+09 | G30: 1.4643094e+09 | H30: 1.2413205e+09 | I30: 9.5743983e+08 | J30: 5.8982615e+08
A31: 其中：消耗性生物资产(元)
A32: 合同资产(元) | B32: 88430040 | C32: 1.2836407e+08 | D32: 90466345 | E32: 53966167 | F32: 41244484
A33: 持有待售资产(元)
A34: 一年内到期的非流动资产(元)
A35: 代理业务资产(元)
A36: 其他流动资产(元) | B36: 66428112 | C36: 61841581 | D36: 1.5322607e+08 | E36: 28413897 | F36: 1376358.4 | G36: 1107640.4 | H36: 9576117 | I36: 31361634 | J36: 46918.39
A37: 流动资产其他项目(元)
A38: 流动资产平衡项目(元)
A39: 流动资产合计(元) | B39: 5.6961726e+09 | C39: 5.9669625e+09 | D39: 5.6484278e+09 | E39: 4.3051458e+09 | F39: 4.0116381e+09 | G39: 3.6029688e+09 | H39: 2515842092 | I39: 1.9372279e+09 | J39: 1.633847e+09
A40: 非流动资产：
A41: 发放委托贷款及垫款(元)
A42: 债权投资(元)
A43: 以摊余成本计量的金融资产（非流动）(元)
A44: 其他债权投资(元)
A45: 以公允价值计量且其变动计入其他综合收益的金融资产（非流动）(元)
A46: 可供出售金融资产(元)
A47: 持有至到期投资(元)
A48: 长期应收款(元)
A49: 长期股权投资(元)
A50: 其他权益工具投资(元)
A51: 其他非流动金融资产(元)
A52: 投资性房地产(元)
A53: 固定资产(元) | B53: 2.276114e+09 | C53: 1.9477146e+09 | D53: 1.5131556e+09 | E53: 8.9710498e+08 | F53: 8.5093249e+08 | G53: 8.0258613e+08 | H53: 8.1331494e+08 | I53: 7.3775951e+08 | J53: 6.7878626e+08
A54: 在建工程(元) | B54: 1.3633064e+08 | C54: 1.5247531e+08 | D54: 2.6176959e+08 | E54: 2.9624944e+08 | F54: 43255468 | G54: 11596390 | H54: 9293134.8 | I54: 20022483 | J54: 6263686.8
A55: 工程物资(元)
A56: 固定资产清理(元)
A57: 生产性生物资产(元)
A58: 油气资产(元)
A59: 使用权资产(元) | B59: 1116002.9 | C59: 1943142.7 | D59: 2951079.1 | E59: 285000
A60: 无形资产(元) | B60: 3.0849576e+08 | C60: 2.8233259e+08 | D60: 2.9068483e+08 | E60: 2.0035943e+08 | F60: 2.0503512e+08 | G60: 1.8379866e+08 | H60: 1.7680859e+08 | I60: 1.819985e+08 | J60: 1.8726502e+08
A61: 开发支出(元)
A62: 商誉(元)
A63: 长期待摊费用(元) | F63: 300000
A64: 递延所得税资产(元) | B64: 1.2828118e+08 | C64: 1.3165272e+08 | D64: 1.4000767e+08 | E64: 120165391 | F64: 1.0199106e+08 | G64: 73572245 | H64: 55275360 | I64: 45300094 | J64: 39922242
A65: 其他非流动资产(元) | B65: 1.2602144e+08 | C65: 1.457071e+08 | D65: 1.1961798e+08 | E65: 1.3142613e+08 | F65: 33768223 | G65: 2669870.4
A66: 非流动资产其他项目(元)
A67: 非流动资产平衡项目(元)
A68: 非流动资产合计(元) | B68: 2.976359e+09 | C68: 2.6618255e+09 | D68: 2.3281867e+09 | E68: 1.6455904e+09 | F68: 1.2352824e+09 | G68: 1.0742233e+09 | H68: 1.054692e+09 | I68: 9.8508058e+08 | J68: 9.122372e+08
A69: 资产其他项目(元)
A70: 资产平衡项目(元)
A71: 资产总计(元) | B71: 8.6725316e+09 | C71: 8.628788e+09 | D71: 7.9766145e+09 | E71: 5.9507361e+09 | F71: 5.2469204e+09 | G71: 4.6771921e+09 | H71: 3.5705341e+09 | I71: 2.9223084e+09 | J71: 2.5460842e+09
A72: 流动负债：
A73: 短期借款(元) | B73: 2.0014667e+08 | C73: 2.0014056e+08
A74: 向中央银行借款(元)
A75: 吸收存款及同业存放(元)
A76: 拆入资金(元)
A77: 交易性金融负债(元)
A78: 衍生金融负债(元)
A79: 应付票据及应付账款(元) | B79: 5.5993173e+08 | C79: 5.3419073e+08 | D79: 5.4879708e+08 | E79: 3.0869669e+08 | F79: 2.7405627e+08 | G79: 2.7016354e+08 | H79: 2.8597084e+08 | I79: 2.4068704e+08 | J79: 1.7778472e+08
A80: 其中：应付票据(元) | B80: 80000000 | C80: 44550000 | D80: 50000000
A81: 应付账款(元) | B81: 4.7993173e+08 | C81: 4.8964073e+08 | D81: 4.9879708e+08 | E81: 3.0869669e+08 | F81: 2.7405627e+08 | G81: 2.7016354e+08
A82: 预收款项(元) | G82: 1.3707367e+09 | H82: 1.0051951e+09 | I82: 6.9091479e+08 | J82: 4.7665683e+08
A83: 合同负债(元) | B83: 2.6158535e+09 | C83: 2.5760381e+09 | D83: 2.1657414e+09 | E83: 1.6822218e+09 | F83: 1.3529625e+09
A84: 卖出回购金融资产款(元)
A85: 应付手续费及佣金(元)
A86: 应付职工薪酬(元) | B86: 3.1120811e+08 | C86: 2.9426793e+08 | D86: 3.0464802e+08 | E86: 2.7592211e+08 | F86: 2.5112894e+08 | G86: 2.6377755e+08 | H86: 1.9505173e+08 | I86: 1.5873964e+08 | J86: 1.5212198e+08
A87: 应交税费(元) | B87: 1.0069529e+08 | C87: 80490706 | D87: 67844728 | E87: 51012812 | F87: 51241834 | G87: 57837229 | H87: 39576322 | I87: 37044960 | J87: 56479355
A88: 其他应付款合计(元) | B88: 65758007 | C88: 1.3226595e+08 | D88: 1.7012334e+08 | E88: 74908070 | F88: 1.3609238e+08 | G88: 8697489.9 | H88: 7798159.9 | I88: 4052284.5 | J88: 2266914.6
A89: 其中：应付利息(元)
A90: 应付股利(元)
A91: 其他应付款(元) | B91: 65758007 | C91: 1.3226595e+08 | D91: 1.7012334e+08 | E91: 74908070 | F91: 1.3609238e+08 | G91: 8697489.9 | H91: 7798159.9 | I91: 4052284.5 | J91: 2266914.6
A92: 应付分保账款(元)
A93: 内部应付款(元)
A94: 预计流动负债(元)
A95: 保险合同准备金(元)
A96: 代理买卖证券款(元)
A97: 代理承销证券款(元)
A98: 一年内的递延收益(元)
A99: 以摊余成本计量的金融负债(元)
A100: 应付短期债券(元)
...

Sheet BS_Analysis
A1: A 列 (项目) | B1: B 列 (数值/公式) | C1: C 列 (说明)
A2: 基础数据
A3: 营业收入 (TTM) | B3: 5.6261559e+09 | C3: 用于估算经营所需现金
A4: 关键假设
A5: 经营现金占收入比例 | B5: 0.02 | C5: 经验值，通常在 0.5% - 2% 之间
A6: 中间计算
A7: 估算经营现金 | B7: =B3*B5 -> 1.1252312e+08 | C7: 这是 OA (经营资产) 的一部分
A8: 估算多余现金 | B8: =[2]原资产负债表!C6-B7 -> 1.8787303e+09 | C8: 这是 FA (金融资产) 的一部分
A12: 类别 | B12: 重构后项目名称 | C12: 建议 Excel 公式 (对应原始报表科目) | D12: 计算 | E12: Penman 逻辑说明
A13: 经营资产 (OA) | B13: 1. 经营性现金 | C13: “=Inputs!B7 | D13: =[2]Inputs!B7 -> 1.1252312e+08 | E13: 维持生意运转必须的“零钱”。
B14: 2. 经营性应收款项 | C14: “=应收票据+应收账款+应收款项融资+预付款项+合同资产+其他应收款(扣除利息/股利) | E14: 所有业务相关的赊销和预付。注：若其他应收款含大额拆解款需剔除。
B15: 3. 存货 | C15: ”=存货+消耗性生物资产+持有待售资产 | E15: 待售的商品，核心经营资产。
B16: 4. 长期经营性投资 | C16: “=长期股权投资 | E16: 假设：这里的长投是对产业链上下游的战略投资。
B17: 5. 固定资产与生产设施 | C17: ”=固定资产+在建工程+工程物资+生产性生物资产+油气资产+固定资产清理 | E17: 典型的重资产经营投入。
B18: 6. 使用权资产 | C18: “=使用权资产 | E18: 新租赁准则下，租来的店面/厂房也是经营资产。
B19: 7. 无形资产与商誉 | C19: ”=无形资产+开发支出+商誉 | E19: 知识产权和并购溢价。
B20: 8. 其他经营性资产 | C20: “=长期待摊费用+递延所得税资产+其他流动资产+其他非流动资产 | E20: 除非附注特别说明是理财，否则默认归为经营。
B21: 经营资产合计 (OA) | C21: =SUM(上述 1-8 项) | E21: 企业的“印钞机”总规模。
A23: 经营负债 (OL) | B23: 9. 经营性应付款项 | C23: ”=应付票据+应付账款+预收款项+合同负债+其他应付款(扣除利息/股利) | E23: 占用供应商和客户的资金，无息负债。
B24: 10. 职工与税务负债 | C24: “=应付职工薪酬+长期应付职工薪酬+应交税费 | E24: 欠员工和税务局的钱。
B25: 11. 经营性预计负债 | C25: ”=预计负债+预计流动负债+递延收益(含一年内) | E25: 产品保修、政府补助递延等。
B26: 12. 其他经营性负债 | C26: “=递延所得税负债+其他流动负债+其他非流动负债 | E26: 伴随经营产生的非金融债务。
B27: 经营负债合计 (OL) | C27: =SUM(上述 9-12 项) | E27: 上下游“免费”借给你的钱。
A29: 核心指标 | B29: 净经营性资产 (NOA) | C29: ”=OA合计-OL合计 | E29: 你需要投入多少真金白银才能转动这个生意。
A31: 对于模棱两可的资产，Penman 的黄金法则：除非你能明确证明它是用来“生利息”的（金融），否则一律默认归为“经营”。（因为我们要做的是计算 RNOA，把不明资产归入经营资产会增加分母，使 RNOA 更保守、更真实）。
A34: 类别 | B34: 重构后项目名称 | C34: 建议 Excel 公式 (对应原始报表科目) | E34: Penman 逻辑说明
A35: 金融负债 (FL) | B35: 1. 短期有息债务 | C35: {=短期借款+交易性金融负债+应付短期债券+拆入资金+卖出回购金融资产款} -> #NAME? | E35: 需要付息的短期钱。
B36: 2. 长期有息债务 | C36: {=长期借款+应付债券+长期应付款(融资性质)} -> #NAME? | E36: 需要付息的长期钱。
B37: 3. 租赁负债 | C37: {=租赁负债+一年内到期的非流动负债(租赁部分)} -> #NAME? | E37: 虽是经营用，但本质是融资行为(付利息)。
B38: 4. 隐性金融负债 | C38: {=一年内到期的非流动负债(借款部分)+应付利息} -> #NAME? | E38: 即将到期的债和欠的利息。
B39: 5. 优先股/永续债 | C39: {=应付债券下的优先股/永续债} -> #NAME? | E39: 注：若在权益科目下，需人工判断是否该挪到这里。
B40: 金融负债合计 (FL) | C40: =SUM(上述 1-5 项) | E40: 要付利息的债务总额。
A42: 金融资产 (FA) | B42: 6. 多余现金 | C42: {=[1]!B8 (来自假设页)} -> #NAME? | E42: 超过经营所需的闲置资金。
B43: 7. 短期理财 | C43: {=交易性金融资产+衍生金融资产+买入返售金融资产} -> #NAME? | E43: 炒股、买基金的钱。
B44: 8. 债权与借贷投资 | C44: {=债权投资+其他债权投资+发放委托贷款及垫款+拆出资金} -> #NAME? | E44: 借给别人赚利息的钱。
B45: 9. 投资性房地产 | C45: {=投资性房地产} -> #NAME? | E45: 注：Penman 通常视为金融资产，除非是地产公司。
B46: 10. 其他金融投资 | C46: {=其他权益工具投资+其他非流动金融资产+应收利息+应收股利} -> #NAME? | E46: 被动持有的股份和投资收益。
B47: 金融资产合计 (FA) | C47: =SUM(上述 6-10 项) | E47: 闲钱和“小金库”。
A49: 核心指标 | B49: 净金融负债 (NFO) | C49: {=FL合计-FA合计} -> #NAME? | E49: 企业的净债务负担。如果是负数，说明不缺钱。
A58: 类别 | B58: 重构后项目名称 | C58: 建议 Excel 公式 (对应原始报表科目) | E58: Penman 逻辑说明
A59: 权益 (SE) | B59: 1. 归属母公司权益 | C59: {=归属于母公司股东权益合计} -> #NAME? | E59: 包含股本、公积、未分利等。
B60: 2. 少数股东权益 | C60: {=少数股东权益} -> #NAME? | E60: 视为广义的权益融资来源。
B61: 3. 应付股利调整 | C61: {=应付股利} -> #NAME? | E61: 关键调整：虽然报表里它是负债，但 Penman 认为钱还没流出，就仍属于股东。
B62: 调整后权益合计 (CSE) | C62: {=项1+项2+项3} -> #NAME? | E62: 重构后的真实股东权益。
A64: 配平检查 | B64: 会计恒等式检查 | C64: {=NOA-NFO-CSE} -> #NAME? | E64: 结果必须为 0。如果不为 0，说明分类有遗漏。

Sheet BS_分类
A1: 科目 | B1: 含义（是什么） | C1: 分类判断要点（怎么分） | D1: 结论（默认：非金融企业）
A2: 流动资产
A3: 货币资金 | B3: 库存现金、银行存款、其他货币资金（常含受限资金） | C3: Penman 通常把现金及现金等价物视为金融资产；但若附注披露有大量经营性受限资金（保证金、信用证/保函保证金、监管专户等），可拆出一部分视作经营性占用 | D3: 金融资产（常需附注拆分“受限/经营性现金”）
A4: 结算备付金 | B4: 在清算机构/交易所的结算备付金（券商/期货常见） | C4: 券商等以经纪清算为主营时是“经营所需”；非金融企业若出现，多为特殊业务/保证金性质，仍偏资金属性 | D4: 通常金融资产（若为券商/期货：更偏经营资产）
A5: 拆出资金 | B5: 同业拆出/拆借给金融机构的资金 | C5: 本质是对外“出借资金”赚利息；对银行等属于经营（放贷/同业） | D5: 金融资产（银行等金融机构：可能是经营资产）
A6: 交易性金融资产 | B6: FVTPL：短期交易性证券、基金、理财、股票等 | C6: 非金融企业一般是闲置资金理财/交易；金融机构若以交易为主营则属经营 | D6: 金融资产（金融机构：可能是经营资产）
A7: 融出资金 | B7: 券商两融业务：向客户融资融券形成的融出资金 | C7: 券商主营；对非金融企业一般不会出现 | D7: 金融资产（券商：更偏经营资产）
A8: 衍生金融资产 | B8: 衍生品公允价值为正形成的资产（远期/期权/掉期等） | C8: 关键看用途：套期保值且与经营风险相关（商品、外汇、利率对冲）→可视作经营相关；投机/交易→金融资产；需要看套期会计、风险管理说明 | D8: 需结合附注具体分析（常见：套保=偏经营；交易=金融）
A9: 应收票据及应收账款 | B9: 因销售商品/服务形成的应收款合计 | C9: 与主营收入直接匹配，通常就是经营周转资金 | D9: 经营资产
A10: 其中：应收票据 | B10: 商业/银行承兑汇票等 | C10: 通常来自销售结算；若公司大量“票据投资/票据套利”需警惕（看附注票据来源与背书贴现） | D10: 通常经营资产（票据投资化时需附注）
A11: 其中：应收账款 | B11: 赊销形成的应收账款 | C11: 典型经营资产 | D11: 经营资产
A12: 应收款项融资 | B12: IFRS9/CAS：以公允价值计量的票据/应收款（常见为票据） | C12: 多数企业是销售回款形态变化（票据），仍与经营相关；但若附注明确为理财型票据/投资性持有则偏金融 | D12: 通常经营资产（可能需附注确认是否“投资化”）
A13: 预付款项 | B13: 预付供应商货款、预付采购款等 | C13: 经营采购链条的一部分 | D13: 经营资产
A14: 应收保费 | B14: 保险公司应收未收的保费 | C14: 保险主营业务形成；非保险企业一般无此科目 | D14: 金融机构（保险）=经营资产；非金融企业：通常不适用
... A36: 流动资产合计 | B36: 流动资产小计 | C36: 汇总行 | D36: 不分类（小计）
A37: 非流动资产
A38: 发放委托贷款及垫款 | B38: 委托贷款（通过银行通道向外放款）及相关垫款 | C38: 本质是对外提供资金、赚取利息；很多时候是非主营“类金融化” | D38: 金融资产（需关注是否为关联方资金占用）
A39: 债权投资 | B39: 新准则下的债权类投资（多与摊余成本/FVOCI相关） | C39: 投资属性强，利息回报 | D39: 金融资产
A40: 以摊余成本计量的金融资产（非流动） | B40: 非流动的摊余成本金融资产（债券、贷款等） | C40: 投资/放款属性 | D40: 金融资产（金融机构：可能经营）
A41: 其他债权投资 | B41: 通常指 FVOCI 债权投资 | C41: 投资属性 | D41: 金融资产
A42: 以公允价值计量且其变动计入其他综合收益的金融资产（非流动） | B42: 非流动FVOCI金融资产 | C42: 投资属性；若是战略持股需附注判断 | D42: 金融资产（战略股权：可提示附注）
A43: 可供出售金融资产 | B43: 旧准则 AFS | C43: 投资属性 | D43: 金融资产
A44: 持有至到期投资 | B44: 旧准则 HTM | C44: 投资属性 | D44: 金融资产
A45: 长期应收款 | B45: 一年以上收回的应收款：分期收款、融资租赁应收款、保证金等 | C45: 关键看形成原因：分期销售/工程结算→经营；融资租赁/对外借款/类放贷→金融 | D45: 需结合附注具体分析
A46: 长期股权投资 | B46: 对子公司/联营合营/长期持股（权益法等） | C46: 若为产业协同、供应链/渠道/资源控制等战略投资，Penman 常把其视为经营性投资的一部分；若纯财务投资则更偏金融；需看投资目的、是否并表/权益法、收益来源 | D46: 通常需结合附注分析（偏“经营性投资”或“金融性投资”）
A47: 其他权益工具投资 | B47: 一般为指定FVOCI的权益工具投资（非交易） | C47: 可能是战略少数股权，也可能是长期财务投资；看是否与主营协同、是否获取分红/公允价值 | D47: 需结合附注具体分析（多数情况偏金融）
A48: 其他非流动金融资产 | B48: 各类非流动金融工具：长期理财、结构性存款、衍生品保证金/投资等 | C48: 名称已指向金融属性，但“里面装什么”差异大，必须看附注明细 | D48: 通常金融资产（但常需附注拆分）
A49: 投资性房地产 | B49: 为赚取租金/资本增值而持有的房地产 | C49: 若公司本身以出租/持有物业为主营（商业地产、REIT平台、酒店物业出租等）→经营资产；若只是闲置物业投资→可视作非核心经营资产（仍不属于金融资产） | D49: 通常经营资产（但建议注明“非主营/投资性经营资产”）
... A68: 资产总计 | B68: 总计 | C68: 汇总行 | D68: 不分类（总计）
A70: 流动负债
A71: 科目 | B71: 含义（是什么） | C71: 分类判断要点（怎么分） | D71: 结论（默认：非金融企业）
A72: 短期借款 | B72: 一年内到期或期限≤1年的银行借款/信用借款等 | C72: 典型计息融资 | D72: 金融负债
A73: 向中央银行借款 | B73: 向央行取得的借款（多见银行） | C73: 银行体系融资来源；银行为经营工具，非金融企业很少出现 | D73: 通常金融负债（银行：更偏经营负债）
A74: 吸收存款及同业存放 | B74: 客户存款、同业存放（多见银行） | C74: 对银行是“原材料/主营资金来源”；对非金融企业通常不出现 | D74: 银行：经营负债；非金融企业：通常不适用/若有则偏金融
A75: 拆入资金 | B75: 同业拆入/短期拆借资金 | C75: 计息融资；金融机构可能作为日常经营资金管理工具 | D75: 金融负债（银行/券商：可能偏经营）
A76: 交易性金融负债 | B76: FVTPL：以交易为目的的金融负债（如卖空、短期交易形成的负债等） | C76: 明显金融属性；若金融机构以交易为主营则偏经营 | D76: 金融负债（金融机构：可能偏经营）
A77: 衍生金融负债 | B77: 衍生品公允价值为负形成的负债 | C77: 关键看用途：**套期保值（对冲经营风险）**可视作经营相关；投机交易为金融；需看套期会计与风险管理披露 | D77: 需结合附注具体分析（套保=偏经营相关；交易=金融）
A78: 应付票据及应付账款 | B78: 采购形成的应付合计 | C78: 供应链信用，经营周转负债 | D78: 经营负债
A79: 其中：应付票据 | B79: 向供应商开具的票据（承兑汇票等） | C79: 属于采购结算与供应链融资的结合；一般仍视作经营性（但若本质是借款替代需关注） | D79: 通常经营负债（若明显融资化可附注调整）
A80: 其中：应付账款 | B80: 赊购形成的应付账款 | C80: 典型经营负债 | D80: 经营负债
A81: 预收款项 | B81: 旧口径：预收客户款项（未履约） | C81: 与销售履约相关 | D81: 经营负债
A82: 合同负债 | B82: 新收入准则：已收/应收对价但尚未履约 | C82: 与主营履约强相关 | D82: 经营负债
... A106: 流动负债合计 | B106: 小计 | C106: 汇总行 | D106: 不分类（小计）
A108: 非流动负债
A109: 科目 | B109: 含义（是什么） | C109: 分类判断要点（怎么分） | D109: 结论（默认：非金融企业）
A110: 长期借款 | B110: 一年以上到期的银行/其他借款 | C110: 计息融资 | D110: 金融负债
A111: 以摊余成本计量的金融负债（非流动） | B111: 非流动的摊余成本金融负债（多为长期借款/债券等） | C111: 计息融资 | D111: 金融负债
A112: 应付债券 | B112: 发行公司债、MTN、中票等形成的债务 | C112: 计息融资 | D112: 金融负债
A113: 其中：优先股 | B113: 会计上若被分类为负债的优先股（取决于是否有强制赎回/强制付息等） | C113: 关键是合同条款：若强制付息/赎回→更像债；若更接近权益（可递延分派、无到期或永续）→估值重构时可能更像权益/类股权 | D113: 需结合附注具体分析（可能在重构中调整为“权益/类权益”）
A114: 其中：永续债 | B114: 永续债/永续中票（会计上分类为负债时） | C114: 同上：看是否永续、是否可递延利息、是否有强制赎回等；估值中常单列处理 | D114: 需结合附注具体分析（可能更像“类权益融资”）
A115: 租赁负债 | B115: 租赁确认的未来租金现值义务 | C115: 本质是类债务（隐含融资），对应使用权资产 | D115: 金融负债
A116: 长期应付款（合计） | B116: 一年以上应付款（设备分期、融资安排、长期往来等） | C116: 很容易“经营/金融混在一起”：若是供应商分期购置设备可能偏经营性信用；若本质是融资性应付款/保理/类借款则偏金融，需看利息、折现、合同条款 | D116: 需结合附注具体分析（不少公司最终应归金融）
A117: 其中：长期应付款 | B117: 上述合计中的明细 | C117: 同上 | D117: 需结合附注具体分析
A118: 其中：专项应付款 | B118: 特定用途款项（政府拨款需专款专用、项目资金等） | C118: 可能更像递延收益/专项资金结算；通常不计息，偏经营性/项目性负债；需看是否需要返还、是否附条件 | D118: 通常经营负债（建议附注确认性质与条件）
A119: 长期应付职工薪酬 | B119: 长期激励、补充养老、离职后福利等长期职工义务 | C119: 经营成本的长期应计 | D119: 经营负债
A120: 预计负债 | B120: 或有事项满足确认条件后的负债（诉讼、担保、质保、退役义务等） | C120: 多数与经营相关→经营负债；若是与融资担保/或债务重组强相关也可能更偏金融；需看预计事项性质 | D120: 通常经营负债（但建议附注确认）
... A129: 负债合计 | B129: 总计 | C129: 汇总行 | D129: 不分类（总计）
A131: 所有者权益

Sheet IS_Input
B1: 2024年年报 | C1: 2023年年报 | D1: 2022年年报 | E1: 2021年年报 | F1: 2020年年报 | G1: 2019年年报 | H1: 2018年年报 | I1: 2017年年报 | J1: 2016年年报
A2: 上市前/上市后 | B2: 上市后 | C2: 上市后 | D2: 上市后 | E2: 上市后 | F2: 上市后 | G2: 上市后 | H2: 上市后 | I2: 上市后 | J2: 上市后
A3: 报表类型 | B3: 合并报表 | C3: 合并报表 | D3: 合并报表 | E3: 合并报表 | F3: 合并报表 | G3: 合并报表 | H3: 合并报表 | I3: 合并报表 | J3: 合并报表
A4: 公司类型 | B4: 通用 | C4: 通用 | D4: 通用 | E4: 通用 | F4: 通用 | G4: 通用 | H4: 通用 | I4: 通用 | J4: 通用
A5: 营业总收入(元) | B5: 6.1294612e+09 | C5: 6.2493191e+09 | D5: 5.6821414e+09 | E5: 4.651101e+09 | F5: 3.3292979e+09 | G5: 3.3108641e+09 | H5: 2.9185729e+09 | I5: 2.2105295e+09 | J5: 1.5443009e+09
A6: 营业收入(元) | B6: 6.1294612e+09 | C6: 6.2493191e+09 | D6: 5.6821414e+09 | E6: 4.651101e+09 | F6: 3.3292979e+09 | G6: 3.3108641e+09 | H6: 2.9185729e+09 | I6: 2.2105295e+09 | J6: 1.5443009e+09
A7: 利息收入(元)
A8: 已赚保费(元)
A9: 手续费及佣金收入(元)
A10: 其他业务收入(元)
A11: 营业总收入其他项目(元)
A12: 营业总成本(元) | B12: 4.986304e+09 | C12: 4.9560308e+09 | D12: 4.6022252e+09 | E12: 3.852266e+09 | F12: 2.6681157e+09 | G12: 2.792297e+09 | H12: 2.6003653e+09 | I12: 1.9640157e+09 | J12: 1.3410793e+09
A13: 营业成本(元) | B13: 4.3484288e+09 | C13: 4.2653276e+09 | D13: 3.9359379e+09 | E13: 3.2561203e+09 | F13: 2.264071e+09 | G13: 2.1602137e+09 | H13: 2.0377264e+09 | I13: 1.5319061e+09 | J13: 9.6943038e+08
A14: 利息支出(元)
A15: 手续费及佣金支出(元)
A16: 退保金(元)
A17: 赔付支出净额(元)
A18: 提取保险合同准备金净额(元)
A19: 保单红利支出(元)
A20: 分保费用(元)
A21: 其他业务成本(元)
A22: 税金及附加(元) | B22: 58993249 | C22: 56153247 | D22: 42917340 | E22: 37532317 | F22: 34089083 | G22: 37951181 | H22: 28000735 | I22: 28023754 | J22: 24206649
A23: 销售费用(元) | B23: 3.0492316e+08 | C23: 2.8585888e+08 | D23: 2.6765168e+08 | E23: 2.2239102e+08 | F23: 1.7217969e+08 | G23: 4.1072375e+08 | H23: 3.4359874e+08 | I23: 2.8617467e+08 | J23: 1.9706339e+08
A24: 管理费用(元) | B24: 1.5168019e+08 | C24: 1.6591343e+08 | D24: 2.0433591e+08 | E24: 2.0784073e+08 | F24: 1.4312881e+08 | G24: 1.2200489e+08 | H24: 1.2830586e+08 | I24: 74180151 | J24: 71364015
A25: 研发费用(元) | B25: 1.5176073e+08 | C25: 2.10426e+08 | D25: 1.8488591e+08 | E25: 1.4155417e+08 | F25: 61678851 | G25: 68644761 | H25: 48742254 | I25: 47311155 | J25: 47605907
A26: 财务费用(元) | B26: -29482145 | C26: -27648392 | D26: -33503537 | E26: -13172586 | F26: -7031743.9 | G26: -7241249.3 | H26: -1345146.9 | I26: 1106103.8 | J26: 1800267
A27: 其中：利息费用(元) | B27: 6249606.8 | C27: 4610251.1 | D27: 1311422.8 | E27: 394228.17 | F27: 74051.02
A28: 减：利息收入(元) | B28: 37086796 | C28: 31023567 | D28: 31991799 | E28: 18258659 | F28: 12674421 | G28: 7073727.4
A29: 资产减值损失(元) | H29: 15336419 | I29: -4686235 | J29: 29608684
A30: 信用减值损失(元)
A31: 营业总成本其他项目(元)
A32: 其他经营收益
A33: 加：其他收益(元) | B33: 18837250 | C33: 10829713 | D33: 11984238 | E33: 5494553 | F33: 7855300.7 | G33: 2762594.7 | H33: 12769314 | I33: 2403689.3
A34: 投资收益(元) | B34: -2192171.2 | C34: -4747780.3 | D34: -4083695.1 | E34: -4737562 | F34: -1168450.1 | G34: 24630.14
A35: 其中：对联营企业和合营企业的投资收益(元)
A36: 以摊余成本计量的金融资产终止确认收益(元) | B36: -3550020.7 | C36: -6928952.9 | D36: -5167716.6 | E36: -4737562 | F36: -1168450.1
A37: 汇兑收益(元)
A38: 净敞口套期收益(元)
A39: 公允价值变动收益(元) | B39: 322384.66 | C39: -7264
A40: 信用减值损失(新)(元) | B40: -39397334 | C40: 231206.7 | D40: -22572029 | E40: 5166307.5 | F40: -8664672.2 | G40: -2168532.8
A41: 资产减值损失(新)(元) | B41: -10215468 | C41: -20696202 | D41: -11634694 | E41: -22210680 | F41: -15172795 | G41: -15133042
A42: 资产处置收益(元) | B42: 15232.5 | C42: 1191740.1 | D42: 631145.05 | E42: 675091.23 | F42: 245980.48 | G42: 1540650.6 | H42: 11527.48 | I42: 2305268.3 | J42: 308680.9
A43: 加：营业利润其他项目(元)
A44: 营业利润平衡项目(元)
A45: 营业利润(元) | B45: 1.1105271e+09 | C45: 1.2800897e+09 | D45: 1.0542412e+09 | E45: 7.8322273e+08 | F45: 6.442776e+08 | G45: 5.0559336e+08 | H45: 3.3098844e+08 | I45: 2.5122278e+08 | J45: 2.0353028e+08
A46: 加：营业外收入(元) | B46: 2203711.2 | C46: 19235765 | D46: 10255086 | E46: 21257909 | F46: 14510146 | G46: 11433902 | H46: 6729888.9 | I46: 13037448 | J46: 7624004
A47: 其中：非流动资产处置利得(元)
A48: 减：营业外支出(元) | B48: 3785485 | C48: 1859631 | D48: 6567274.7 | E48: 3753786.6 | F48: 6357013.7 | G48: 2404846.4 | H48: 7689487.6 | I48: 8286486.8 | J48: 8733266.5
A49: 其中：非流动资产处置净损失(元)
A50: 加：影响利润总额的其他项目(元)
A51: 利润总额平衡项目(元)
A52: 利润总额(元) | B52: 1.1089453e+09 | C52: 1.2974659e+09 | D52: 1.057929e+09 | E52: 8.0072685e+08 | F52: 6.5243073e+08 | G52: 5.1462241e+08 | H52: 3.3002884e+08 | I52: 2.5597374e+08 | J52: 2.0242102e+08
A53: 减：所得税费用(元) | B53: 2.6071413e+08 | C53: 2.8937641e+08 | D53: 2.2401035e+08 | E53: 1.5372077e+08 | F53: 1.3774816e+08 | G53: 1.0154546e+08 | H53: 85553107 | I53: 50017037 | J53: 42676057
A54: 加：未确认投资损失(元)
A55: 加：影响净利润的其他项目(元)
A56: 净利润(元) | B56: 8.4823119e+08 | C56: 1.0080895e+09 | D56: 8.3391867e+08 | E56: 6.4700609e+08 | F56: 5.1468257e+08 | G56: 4.1307695e+08 | H56: 2.4447574e+08 | I56: 2.059567e+08 | J56: 1.5974496e+08
A57: 其中：被合并方在合并前实现利润(元)
A58: (一)按经营持续性分类
A59: 持续经营净利润(元) | B59: 8.4823119e+08 | C59: 1.0080895e+09 | D59: 8.3391867e+08 | E59: 6.4700609e+08 | F59: 5.1468257e+08 | G59: 4.1307695e+08
A60: 终止经营净利润(元)
A61: (二)按所有权归属分类
A62: 归属于母公司股东的净利润(元) | B62: 8.4823119e+08 | C62: 1.0080895e+09 | D62: 8.3391867e+08 | E62: 6.4700609e+08 | F62: 5.1468257e+08 | G62: 4.1307695e+08 | H62: 2.4447574e+08 | I62: 2.059567e+08 | J62: 1.5974496e+08
A63: 少数股东损益(元)
A64: 扣除非经常性损益后的净利润(元) | B64: 8.407879e+08 | C64: 9.8726377e+08 | D64: 8.2465309e+08 | E64: 6.2957874e+08 | F64: 4.9866003e+08 | G64: 4.0116037e+08 | H64: 236858700 | I64: 198998200 | J64: 160345400
A65: 净利润其他项目(元)
A66: 净利润差额(合计平衡项目)(元)
A67: 其他综合收益(元)
A68: 归属于母公司股东的其他综合收益(元)
A69: 归属于少数股东的其他综合收益(元)
A70: 综合收益总额(元) | B70: 8.4823119e+08 | C70: 1.0080895e+09 | D70: 8.3391867e+08 | E70: 6.4700609e+08 | F70: 5.1468257e+08 | G70: 4.1307695e+08 | H70: 2.4447574e+08 | I70: 2.059567e+08 | J70: 1.5974496e+08
A71: 归属于母公司股东的综合收益总额(元) | B71: 8.4823119e+08 | C71: 1.0080895e+09 | D71: 8.3391867e+08 | E71: 6.4700609e+08 | F71: 5.1468257e+08 | G71: 4.1307695e+08 | H71: 2.4447574e+08 | I71: 2.059567e+08 | J71: 1.5974496e+08
A72: 归属于少数股东的综合收益总额(元)
A73: 每股收益
A74: (一)基本每股收益(元) | B74: 1.49 | C74: 1.78 | D74: 1.49 | E74: 1.63 | F74: 1.29 | G74: 1.1 | H74: 0.68 | I74: 0.57 | J74: 0.44
A75: (二)稀释每股收益(元) | B75: 1.49 | C75: 1.78 | D75: 1.49 | E75: 1.62 | F75: 1.29 | G75: 1.1 | H75: 0.68 | I75: 0.57 | J75: 0.44
A76: 转换汇率 | B76: 1 | C76: 1 | D76: 1 | E76: 1 | F76: 1 | G76: 1 | H76: 1 | I76: 1 | J76: 1
A77: 公告日期 | B77: 2025-04-23 | C77: 2024-04-25 | D77: 2023-04-27 | E77: 2022-04-08 | F77: 2021-04-13 | G77: 2020-04-30 | H77: 2019-03-25 | I77: 2018-03-09 | J77: 2017-03-31
A78: 数据来源 | B78: 年度报告 | C78: 年度报告 | D78: 年度报告 | E78: 年度报告 | F78: 年度报告 | G78: 年度报告 | H78: 招股说明书 | I78: 招股说明书 | J78: 招股说明书
A79: 审计意见(境内) | B79: 标准无保留意见 | C79: 标准无保留意见 | D79: 标准无保留意见 | E79: 标准无保留意见 | F79: 标准无保留意见 | G79: 标准无保留意见 | H79: 标准无保留意见 | I79: 标准无保留意见 | J79: 标准无保留意见
A85: 数据来源：妙想Choice

Sheet IS_Analysis
C1: 说明 | D1: 2024A | E1: 2023A | F1: 2022A | G1: 2021A | H1: 2020A | I1: 2019A | J1: 2018A | K1: 2017A | L1: 2016A
B2: 法定所得税率 (t) | C2: 一般为 25%，高新企业 15%。用于计算税盾。 | D2: 0.25
B3: 报表净利润 | C3: 用于最后核对是否配平。 | D3: =IS_Input!B56 -> 8.4823119e+08 | E3: =IS_Input!C56 -> 1.0080895e+09 | F3: =IS_Input!D56 -> 8.3391867e+08 | G3: =IS_Input!E56 -> 6.4700609e+08 | H3: =IS_Input!F56 -> 5.1468257e+08 | I3: =IS_Input!G56 -> 4.1307695e+08 | J3: =IS_Input!H56 -> 2.4447574e+08 | K3: =IS_Input!I56 -> 2.059567e+08 | L3: =IS_Input!J56 -> 1.5974496e+08
B4: 报表所得税 | D4: =IS_Input!B53 -> 2.6071413e+08 | E4: =IS_Input!C53 -> 2.8937641e+08 | F4: =IS_Input!D53 -> 2.2401035e+08 | G4: =IS_Input!E53 -> 1.5372077e+08 | H4: =IS_Input!F53 -> 1.3774816e+08 | I4: =IS_Input!G53 -> 1.0154546e+08 | J4: =IS_Input!H53 -> 85553107 | K4: =IS_Input!I53 -> 50017037 | L4: =IS_Input!J53 -> 42676057
A8: 计算税前净金融费用
A9: 行号 | B9: 项目 | C9: Penman 逻辑 | D9: 2024A | E9: 2023A | F9: 2022A | G9: 2021A | H9: 2020A | I9: 2019A | J9: 2018A | K9: 2017A | L9: 2016A
A10: 10 | B10: 金融利息支出 | C10: 借钱的成本。 | D10: =IS_Input!B27 -> 6249606.8 | E10: =IS_Input!C27 -> 4610251.1 | F10: =IS_Input!D27 -> 1311422.8 | G10: =IS_Input!E27 -> 394228.17 | H10: =IS_Input!F27 -> 74051.02 | I10: =IS_Input!G27 -> 0 | J10: =IS_Input!H27 -> 0 | K10: =IS_Input!I27 -> 0 | L10: =IS_Input!J27 -> 0
A11: 11 | B11: (减) 金融利息收入 | C11: 存款/理财的收益。 | D11: =IS_Input!B28 -> 37086796 | E11: =IS_Input!C28 -> 31023567 | F11: =IS_Input!D28 -> 31991799 | G11: =IS_Input!E28 -> 18258659 | H11: =IS_Input!F28 -> 12674421 | I11: =IS_Input!G28 -> 7073727.4 | J11: =IS_Input!H28 -> 0 | K11: =IS_Input!I28 -> 0 | L11: =IS_Input!J28 -> 0
A12: 12 | B12: (减) 金融投资收益 | C12: 假设：除了联营合营外，其他都是炒股收益。 | D12: =IS_Input!B34-IS_Input!B35 -> -2192171.2 | E12: =IS_Input!C34-IS_Input!C35 -> -4747780.3 | F12: =IS_Input!D34-IS_Input!D35 -> -4083695.1 | G12: =IS_Input!E34-IS_Input!E35 -> -4737562 | H12: =IS_Input!F34-IS_Input!F35 -> -1168450.1 | I12: =IS_Input!G34-IS_Input!G35 -> 24630.14 | J12: =IS_Input!H34-IS_Input!H35 -> 0 | K12: =IS_Input!I34-IS_Input!I35 -> 0 | L12: =IS_Input!J34-IS_Input!J35 -> 0
A13: 13 | B13: (减) 公允价值变动 | C13: 假设：默认全是理财产品的波动。 | D13: =IS_Input!B39 -> 322384.66 | E13: =IS_Input!C39 -> -7264 | F13: =IS_Input!D39 -> 0 | G13: =IS_Input!E39 -> 0 | H13: =IS_Input!F39 -> 0 | I13: =IS_Input!G39 -> 0 | J13: =IS_Input!H39 -> 0 | K13: =IS_Input!I39 -> 0 | L13: =IS_Input!J39 -> 0
A14: 14 | B14: 税前净金融费用 (Net Interest) | C14: 如果结果是负数，说明公司靠炒股赚的比借钱利息还多。 | D14: =D10-D11-D12-D13 -> -28967402 | E14: =E10-E11-E12-E13 -> -21658272 | F14: =F10-F11-F12-F13 -> -26596682 | G14: =G10-G11-G12-G13 -> -13126869 | H14: =H10-H11-H12-H13 -> -11431920 | I14: =I10-I11-I12-I13 -> -7098357.6 | J14: =J10-J11-J12-J13 -> 0 | K14: =K10-K11-K12-K13 -> 0 | L14: =L10-L11-L12-L13 -> 0
A19: 计算“税盾”与“经营所得税”
A20: 20 | B20: 利息税盾 | C20: 只有净金融费用产生税盾。(若 B14 为负，则产生税务负担) | D20: =D14*$D$2 -> -7241850.6 | E20: =E14*$D$2 -> -5414568 | F20: =F14*$D$2 -> -6649170.4 | G20: =G14*$D$2 -> -3281717.3 | H20: =H14*$D$2 -> -2857980.1 | I20: =I14*$D$2 -> -1774589.4 | J20: =J14*$D$2 -> 0 | K20: =K14*$D$2 -> 0 | L20: =L14*$D$2 -> 0
A21: 21 | B21: 经营活动所得税 | C21: 报表税费 + 税盾 = 经营本身该交的税。 | D21: =D4+D20 -> 2.5347228e+08 | E21: =E4+E20 -> 2.8396184e+08 | F21: =F4+F20 -> 2.1736118e+08 | G21: =G4+G20 -> 1.5043905e+08 | H21: =H4+H20 -> 1.3489018e+08 | I21: =I4+I20 -> 99770875 | J21: =J4+J20 -> 85553107 | K21: =K4+K20 -> 50017037 | L21: =L4+L20 -> 42676057
A29: 重构核心指标 (NOPAT & NFE)
A30: 30 | B30: 税前经营利润 | C30: 利润总额把金融费用加回去，就是经营利润。 | D30: =IS_Input!B52+D14 -> 1.0799779e+09 | E30: =IS_Input!C52+E14 -> 1.2758076e+09 | F30: =IS_Input!D52+F14 -> 1.0313323e+09 | G30: =IS_Input!E52+G14 -> 7.8759998e+08 | H30: =IS_Input!F52+H14 -> 6.4099881e+08 | I30: =IS_Input!G52+I14 -> 5.0752406e+08 | J30: =IS_Input!H52+J14 -> 3.3002884e+08 | K30: =IS_Input!I52+K14 -> 2.5597374e+08 | L30: =IS_Input!J52+L14 -> 2.0242102e+08
A31: 31 | B31: (减) 经营活动所得税 | C31: 减去还原后的经营税负。 | D31: =D21 -> 2.5347228e+08 | E31: =E21 -> 2.8396184e+08 | F31: =F21 -> 2.1736118e+08 | G31: =G21 -> 1.5043905e+08 | H31: =H21 -> 1.3489018e+08 | I31: =I21 -> 99770875 | J31: =J21 -> 85553107 | K31: =K21 -> 50017037 | L31: =L21 -> 42676057
A32: 32 | B32: 税后净经营利润 (NOPAT) | C32: 【核心产出 1】 企业的真实造血能力。 | D32: =D30-D31 -> 8.2650564e+08 | E32: =E30-E31 -> 9.9184575e+08 | F32: =F30-F31 -> 8.1397116e+08 | G32: =G30-G31 -> 6.3716093e+08 | H32: =H30-H31 -> 5.0610863e+08 | I32: =I30-I31 -> 4.0775318e+08 | J32: =J30-J31 -> 2.4447574e+08 | K32: =K30-K31 -> 2.059567e+08 | L32: =L30-L31 -> 1.5974496e+08
A33: 33 | B33: 税前净金融费用 | C33: 同行 14。 | D33: =D14 -> -28967402 | E33: =E14 -> -21658272 | F33: =F14 -> -26596682 | G33: =G14 -> -13126869 | H33: =H14 -> -11431920 | I33: =I14 -> -7098357.6 | J33: =J14 -> 0 | K33: =K14 -> 0 | L33: =L14 -> 0
A34: 34 | B34: (减) 利息税盾 | C34: 税盾抵消了一部分利息成本。 | D34: =D20 -> -7241850.6 | E34: =E20 -> -5414568 | F34: =F20 -> -6649170.4 | G34: =G20 -> -3281717.3 | H34: =H20 -> -2857980.1 | I34: =I20 -> -1774589.4 | J34: =J20 -> 0 | K34: =K20 -> 0 | L34: =L20 -> 0
A35: 35 | B35: 税后净金融费用 (NFE) | C35: 【核心产出 2】 企业的真实融资成本。 | D35: =D33-D34 -> -21725552 | E35: =E33-E34 -> -16243704 | F35: =F33-F34 -> -19947511 | G35: =G33-G34 -> -9845151.9 | H35: =H33-H34 -> -8573940.2 | I35: =I33-I34 -> -5323768.2 | J35: =J33-J34 -> 0 | K35: =K33-K34 -> 0 | L35: =L33-L34 -> 0
A39: 综合收益核对
A40: 40 | B40: 重构净利润 | C40: NOPAT - NFE 应该等于净利润。 | D40: =D32-D35 -> 8.4823119e+08 | E40: =E32-E35 -> 1.0080895e+09 | F40: =F32-F35 -> 8.3391867e+08 | G40: =G32-G35 -> 6.4700609e+08 | H40: =H32-H35 -> 5.1468257e+08 | I40: =I32-I35 -> 4.1307695e+08 | J40: =J32-J35 -> 2.4447574e+08 | K40: =K32-K35 -> 2.059567e+08 | L40: =L32-L35 -> 1.5974496e+08
A41: 41 | B41: 配平误差 | C41: 必须为 0。如果不为 0，检查公式。 | D41: =D40-D3 -> 0 | E41: =E40-E3 -> 0 | F41: =F40-F3 -> 0 | G41: =G40-G3 -> 0 | H41: =H40-H3 -> 0 | I41: =I40-I3 -> 0 | J41: =J40-J3 -> 0 | K41: =K40-K3 -> 0 | L41: =L40-L3 -> 0
A42: 42 | B42: 其他综合收益(OCI) | D42: =IS_Input!B67 -> 0 | E42: =IS_Input!C67 -> 0 | F42: =IS_Input!D67 -> 0 | G42: =IS_Input!E67 -> 0 | H42: =IS_Input!F67 -> 0 | I42: =IS_Input!G67 -> 0 | J42: =IS_Input!H67 -> 0 | K42: =IS_Input!I67 -> 0 | L42: =IS_Input!J67 -> 0
A43: 43 | B43: 综合收益总额 | C43: 估值的真正起点。 | D43: =D40+D42 -> 8.4823119e+08 | E43: =E40+E42 -> 1.0080895e+09 | F43: =F40+F42 -> 8.3391867e+08 | G43: =G40+G42 -> 6.4700609e+08 | H43: =H40+H42 -> 5.1468257e+08 | I43: =I40+I42 -> 4.1307695e+08 | J43: =J40+J42 -> 2.4447574e+08 | K43: =K40+K42 -> 2.059567e+08 | L43: =L40+L42 -> 1.5974496e+08
A47: 比率计算

Sheet IS_分类
B1: 分类 | C1: 2025年三季报 | D1: 2024年年报 | E1: 2023年年报 | F1: 2022年年报 | G1: 2021年年报 | H1: 2020年年报 | I1: 2019年年报 | J1: 2018年年报 | K1: 2017年年报 | L1: 2016年年报
A2: 上市前/上市后 | C2: 上市后 | D2: 上市后 | E2: 上市后 | F2: 上市后 | G2: 上市后 | H2: 上市后 | I2: 上市后 | J2: 上市后 | K2: 上市后 | L2: 上市后
A3: 报表类型 | C3: 合并报表 | D3: 合并报表 | E3: 合并报表 | F3: 合并报表 | G3: 合并报表 | H3: 合并报表 | I3: 合并报表 | J3: 合并报表 | K3: 合并报表 | L3: 合并报表
A4: 公司类型 | C4: 通用 | D4: 通用 | E4: 通用 | F4: 通用 | G4: 通用 | H4: 通用 | I4: 通用 | J4: 通用 | K4: 通用 | L4: 通用
A5: 营业总收入(元) | C5: 4.2004467e+09 | D5: 6.1294612e+09 | E5: 6.2493191e+09 | F5: 5.6821414e+09 | G5: 4.651101e+09 | H5: 3.3292979e+09 | I5: 3.3108641e+09 | J5: 2.9185729e+09 | K5: 2.2105295e+09 | L5: 1.5443009e+09
A6: 营业收入(元) | B6: O | C6: 4.2004467e+09 | D6: 6.1294612e+09 | E6: 6.2493191e+09 | F6: 5.6821414e+09 | G6: 4.651101e+09 | H6: 3.3292979e+09 | I6: 3.3108641e+09 | J6: 2.9185729e+09 | K6: 2.2105295e+09 | L6: 1.5443009e+09
A7: 利息收入(元)
A8: 已赚保费(元)
A9: 手续费及佣金收入(元)
A10: 其他业务收入(元) | B10: O
A11: 营业总收入其他项目(元)
A12: 营业总成本(元) | C12: 3.6059734e+09 | D12: 4.986304e+09 | E12: 4.9560308e+09 | F12: 4.6022252e+09 | G12: 3.852266e+09 | H12: 2.6681157e+09 | I12: 2.792297e+09 | J12: 2.6003653e+09 | K12: 1.9640157e+09 | L12: 1.3410793e+09
A13: 营业成本(元) | B13: O | C13: 3.1724647e+09 | D13: 4.3484288e+09 | E13: 4.2653276e+09 | F13: 3.9359379e+09 | G13: 3.2561203e+09 | H13: 2.264071e+09 | I13: 2.1602137e+09 | J13: 2.0377264e+09 | K13: 1.5319061e+09 | L13: 9.6943038e+08
A14: 利息支出(元)
A15: 手续费及佣金支出(元)
A16: 退保金(元)
A17: 赔付支出净额(元)
A18: 提取保险合同准备金净额(元)
A19: 保单红利支出(元)
A20: 分保费用(元)
A21: 其他业务成本(元)
A22: 税金及附加(元) | B22: O | C22: 35172662 | D22: 58993249 | E22: 56153247 | F22: 42917340 | G22: 37532317 | H22: 34089083 | I22: 37951181 | J22: 28000735 | K22: 28023754 | L22: 24206649
A23: 销售费用(元) | B23: O | C23: 2.3023371e+08 | D23: 3.0492316e+08 | E23: 2.8585888e+08 | F23: 2.6765168e+08 | G23: 2.2239102e+08 | H23: 1.7217969e+08 | I23: 4.1072375e+08 | J23: 3.4359874e+08 | K23: 2.8617467e+08 | L23: 1.9706339e+08
A24: 管理费用(元) | B24: O | C24: 1.0560943e+08 | D24: 1.5168019e+08 | E24: 1.6591343e+08 | F24: 2.0433591e+08 | G24: 2.0784073e+08 | H24: 1.4312881e+08 | I24: 1.2200489e+08 | J24: 1.2830586e+08 | K24: 74180151 | L24: 71364015
A25: 研发费用(元) | B25: O | C25: 78335950 | D25: 1.5176073e+08 | E25: 2.10426e+08 | F25: 1.8488591e+08 | G25: 1.4155417e+08 | H25: 61678851 | I25: 68644761 | J25: 48742254 | K25: 47311155 | L25: 47605907
A26: 财务费用(元) | B26: 分类 | C26: -15843049 | D26: -29482145 | E26: -27648392 | F26: -33503537 | G26: -13172586 | H26: -7031743.9 | I26: -7241249.3 | J26: -1345146.9 | K26: 1106103.8 | L26: 1800267
A27: 其中：利息费用(元) | B27: F | C27: 5349900.6 | D27: 6249606.8 | E27: 4610251.1 | F27: 1311422.8 | G27: 394228.17 | H27: 74051.02
A28: 减：利息收入(元) | B28: F | C28: 17216770 | D28: 37086796 | E28: 31023567 | F28: 31991799 | G28: 18258659 | H28: 12674421 | I28: 7073727.4
A29: 资产减值损失(元) | B29: O | J29: 15336419 | K29: -4686235 | L29: 29608684
A30: 信用减值损失(元) | B30: O
A31: 营业总成本其他项目(元)
A32: 其他经营收益
A33: 加：其他收益(元) | B33: O | C33: 14264614 | D33: 18837250 | E33: 10829713 | F33: 11984238 | G33: 5494553 | H33: 7855300.7 | I33: 2762594.7 | J33: 12769314 | K33: 2403689.3
A34: 投资收益(元) | C34: -1387970 | D34: -2192171.2 | E34: -4747780.3 | F34: -4083695.1 | G34: -4737562 | H34: -1168450.1 | I34: 24630.14
A35: 其中：对联营企业和合营企业的投资收益(元) | B35: O
A36: 以摊余成本计量的金融资产终止确认收益(元) | B36: F | C36: -2253614.8 | D36: -3550020.7 | E36: -6928952.9 | F36: -5167716.6 | G36: -4737562 | H36: -1168450.1
A37: 汇兑收益(元) | B37: O
A38: 净敞口套期收益(元) | B38: O
A39: 公允价值变动收益(元) | B39: F(拆分） | C39: 1029767.1 | D39: 322384.66 | E39: -7264
A40: 信用减值损失(新)(元) | B40: O | C40: -14560864 | D40: -39397334 | E40: 231206.7 | F40: -22572029 | G40: 5166307.5 | H40: -8664672.2 | I40: -2168532.8
A41: 资产减值损失(新)(元) | B41: O | C41: -13023849 | D41: -10215468 | E41: -20696202 | F41: -11634694 | G41: -22210680 | H41: -15172795 | I41: -15133042
A42: 资产处置收益(元) | B42: O | D42: 15232.5 | E42: 1191740.1 | F42: 631145.05 | G42: 675091.23 | H42: 245980.48 | I42: 1540650.6 | J42: 11527.48 | K42: 2305268.3 | L42: 308680.9
A43: 加：营业利润其他项目(元)
A44: 营业利润平衡项目(元)
A45: 营业利润(元) | C45: 5.8079504e+08 | D45: 1.1105271e+09 | E45: 1.2800897e+09 | F45: 1.0542412e+09 | G45: 7.8322273e+08 | H45: 6.442776e+08 | I45: 5.0559336e+08 | J45: 3.3098844e+08 | K45: 2.5122278e+08 | L45: 2.0353028e+08
A46: 加：营业外收入(元) | B46: O | C46: 2374641.2 | D46: 2203711.2 | E46: 19235765 | F46: 10255086 | G46: 21257909 | H46: 14510146 | I46: 11433902 | J46: 6729888.9 | K46: 13037448 | L46: 7624004
A47: 其中：非流动资产处置利得(元) | B47: O
A48: 减：营业外支出(元) | B48: O | C48: 2440630.4 | D48: 3785485 | E48: 1859631 | F48: 6567274.7 | G48: 3753786.6 | H48: 6357013.7 | I48: 2404846.4 | J48: 7689487.6 | K48: 8286486.8 | L48: 8733266.5
A49: 其中：非流动资产处置净损失(元) | B49: O
A50: 加：影响利润总额的其他项目(元)
A51: 利润总额平衡项目(元)
A52: 利润总额(元) | C52: 5.8072905e+08 | D52: 1.1089453e+09 | E52: 1.2974659e+09 | F52: 1.057929e+09 | G52: 8.0072685e+08 | H52: 6.5243073e+08 | I52: 5.1462241e+08 | J52: 3.3002884e+08 | K52: 2.5597374e+08 | L52: 2.0242102e+08
A53: 减：所得税费用(元) | B53: Tax | C53: 1.4531754e+08 | D53: 2.6071413e+08 | E53: 2.8937641e+08 | F53: 2.2401035e+08 | G53: 1.5372077e+08 | H53: 1.3774816e+08 | I53: 1.0154546e+08 | J53: 85553107 | K53: 50017037 | L53: 42676057
A54: 加：未确认投资损失(元)
A55: 加：影响净利润的其他项目(元)
A56: 净利润(元) | C56: 4.3541151e+08 | D56: 8.4823119e+08 | E56: 1.0080895e+09 | F56: 8.3391867e+08 | G56: 6.4700609e+08 | H56: 5.1468257e+08 | I56: 4.1307695e+08 | J56: 2.4447574e+08 | K56: 2.059567e+08 | L56: 1.5974496e+08
A57: 其中：被合并方在合并前实现利润(元)
A58: (一)按经营持续性分类
A59: 持续经营净利润(元) | C59: 4.3541151e+08 | D59: 8.4823119e+08 | E59: 1.0080895e+09 | F59: 8.3391867e+08 | G59: 6.4700609e+08 | H59: 5.1468257e+08 | I59: 4.1307695e+08
A60: 终止经营净利润(元)
A61: (二)按所有权归属分类
A62: 归属于母公司股东的净利润(元) | C62: 4.3541151e+08 | D62: 8.4823119e+08 | E62: 1.0080895e+09 | F62: 8.3391867e+08 | G62: 6.4700609e+08 | H62: 5.1468257e+08 | I62: 4.1307695e+08 | J62: 2.4447574e+08 | K62: 2.059567e+08 | L62: 1.5974496e+08
A63: 少数股东损益(元)
A64: 扣除非经常性损益后的净利润(元) | C64: 4.2585235e+08 | D64: 8.407879e+08 | E64: 9.8726377e+08 | F64: 8.2465309e+08 | G64: 6.2957874e+08 | H64: 4.9866003e+08 | I64: 4.0116037e+08 | J64: 236858700 | K64: 198998200 | L64: 160345400
A65: 净利润其他项目(元)
A66: 净利润差额(合计平衡项目)(元)
A67: 其他综合收益(元) | B67: 拆分
A68: 归属于母公司股东的其他综合收益(元)
A69: 归属于少数股东的其他综合收益(元)
A70: 综合收益总额(元) | C70: 4.3541151e+08 | D70: 8.4823119e+08 | E70: 1.0080895e+09 | F70: 8.3391867e+08 | G70: 6.4700609e+08 | H70: 5.1468257e+08 | I70: 4.1307695e+08 | J70: 2.4447574e+08 | K70: 2.059567e+08 | L70: 1.5974496e+08
A71: 归属于母公司股东的综合收益总额(元) | C71: 4.3541151e+08 | D71: 8.4823119e+08 | E71: 1.0080895e+09 | F71: 8.3391867e+08 | G71: 6.4700609e+08 | H71: 5.1468257e+08 | I71: 4.1307695e+08 | J71: 2.4447574e+08 | K71: 2.059567e+08 | L71: 1.5974496e+08
A72: 归属于少数股东的综合收益总额(元)
A73: 每股收益
A74: (一)基本每股收益(元) | C74: 0.76 | D74: 1.49 | E74: 1.78 | F74: 1.49 | G74: 1.63 | H74: 1.29 | I74: 1.1 | J74: 0.68 | K74: 0.57 | L74: 0.44
A75: (二)稀释每股收益(元) | C75: 0.76 | D75: 1.49 | E75: 1.78 | F75: 1.49 | G75: 1.62 | H75: 1.29 | I75: 1.1 | J75: 0.68 | K75: 0.57 | L75: 0.44
A76: 转换汇率 | C76: 1 | D76: 1 | E76: 1 | F76: 1 | G76: 1 | H76: 1 | I76: 1 | J76: 1 | K76: 1 | L76: 1
A77: 公告日期 | C77: 2025-10-30 | D77: 2025-04-23 | E77: 2024-04-25 | F77: 2023-04-27 | G77: 2022-04-08 | H77: 2021-04-13 | I77: 2020-04-30 | J77: 2019-03-25 | K77: 2018-03-09 | L77: 2017-03-31
A78: 数据来源 | C78: 三季度报告 | D78: 年度报告 | E78: 年度报告 | F78: 年度报告 | G78: 年度报告 | H78: 年度报告 | I78: 年度报告 | J78: 招股说明书 | K78: 招股说明书 | L78: 招股说明书
A79: 审计意见(境内) | C79: - | D79: 标准无保留意见 | E79: 标准无保留意见 | F79: 标准无保留意见 | G79: 标准无保留意见 | H79: 标准无保留意见 | I79: 标准无保留意见 | J79: 标准无保留意见 | K79: 标准无保留意见 | L79: 标准无保留意见

Sheet 指标分析
A1: 核心驱动分析
A2: 行号 | B2: 项目 (Item) | C2: Excel 计算公式逻辑 | D2: 数据计算 | E2: Penman 深度解读
A3: A | B3: 基础数据引用
A4: 1 | B4: 营业收入 | C4: {=[3]!营业收入} -> #NAME? | E4: 分母基数。
A5: 2 | B5: 税后净经营利润 (NOPAT) | C5: {=[3]!NOPAT} -> #NAME? | E5: 核心造血成果。
A6: 3 | B6: 税后净金融费用 (NFE) | C6: {=[3]!NFE} -> #NAME? | E6: 债务融资成本。
A7: 4 | B7: 平均净经营资产 (Avg. NOA) | C7: {=(期初NOA+期末NOA)/2} -> #NAME? | E7: 注意：流量/存量比率，分母必须用平均值！
A8: 5 | B8: 平均净金融负债 (Avg. NFO) | C8: {=(期初NFO+期末NFO)/2} -> #NAME? | E8: 同上。
A9: 6 | B9: 平均股东权益 (Avg. CSE) | C9: {=(期初CSE+期末CSE)/2} -> #NAME? | E9: 同上。
A11: B | B11: 获利能力指标 (Profitability)
A12: 7 | B12: RNOA (净经营资产回报率) | C12: {=NOPAT/Avg.NOA} -> #NAME? | E12: 【皇冠上的明珠】<br>衡量企业“印钞机”的效率。<br>优秀标准：>15% (且高于加权平均资本成本)
A13: 8 | B13: NBC (净借款成本率) | C13: {=NFE/Avg.NFO} -> #NAME? | E13: 【融资底线】<br>衡量借钱的税后成本。<br>看点：如果 RNOA > NBC，说明借钱能放大收益；反之则会亏得更惨。
A14: 9 | B14: ROE (重构后) | C14: {=RNOA+(FLEV*(RNOA-NBC))} -> #NAME? | E14: 【杠杆效应公式】<br>这是 Penman 最经典的恒等式。<br>它告诉你：ROE 高是因为业务好 (RNOA)，还是因为敢借钱 (Leverage)？
A16: C | B16: 驱动因素分解 (DuPont Breakdown)
A17: 10 | B17: 经营利润率 (PM) | C17: {=NOPAT/营业收入} -> #NAME? | E17: 【卖得贵不贵？】<br>反映产品定价权和成本控制力。<br>茅台模式：高 PM，低 ATO
A18: 11 | B18: 资产周转率 (ATO) | C18: {=营业收入/Avg.NOA} -> #NAME? | E18: 【卖得快不快？】<br>反映资产管理效率。<br>沃尔玛模式：低 PM，高 ATO
A19: 12 | B19: 验证 RNOA | C19: {=PM*ATO} -> #NAME? | E19: 必须等于行 7 的结果。
A22: 杠杆与风险分析 (Leverage & Risk)
A23: 行号 | B23: 项目 (Item) | C23: Excel 计算公式逻辑 | E23: Penman 深度解读
A24: D | B24: 杠杆比率 (Leverage Ratios)
A25: 13 | B25: 金融杠杆 (FLEV) | C25: {=Avg.NFO/Avg.CSE} -> #NAME? | E25: 【敢不敢借钱】<br>也就是净负债率。FLEV 越高，ROE 波动越剧烈（风险越大）。
A26: 14 | B26: 经营负债杠杆 (OLLEV) | C26: {=Avg.OL/Avg.NOA} -> #NAME? | E26: 【能不能占用上下游资金】<br>这是 Penman 特有的指标。<br>公式含义：经营资产里有多少是供应商“免费”赞助的？<br>解读：越高越好（如戴尔、亚马逊），说明资金占用能力极强。
A28: E | B28: 流动性与结构 (Structure)
A29: 15 | B29: 现金含量 | C29: {=经营现金/营业收入} -> #NAME? | E29: 验证 Input 页的假设是否合理。
A30: 16 | B30: 核心资产占比 | C30: {=固定资产/OA总额} -> #NAME? | E30: 越高说明越重资产，转型越难。
A40: 行号 | B40: 项目 (Item) | C40: Excel 计算公式逻辑 | E40: Penman 深度解读
A41: F | B41: 剩余经营收益 (ReOI)
A42: 17 | B42: 本期 NOPAT | C42: {=行2} -> #NAME? | E42: 实际赚的钱。
A43: 18 | B43: 期初 NOA | C43: {=[4]!期初NOA} -> #NAME? | E43: 注意：这里用期初数，不是平均数。因为是期初投入的资本在这一年产生的回报。
A44: 19 | B44: 要求回报率 | C44: 输入假设值 (如 10%) | E44: 资本的租金。
A45: 20 | B45: 资本成本 (Capital Charge) | C45: {=期初NOA*要求回报率} -> #NAME? | E45: 你理应赚到的钱（及格线）。
A46: 21 | B46: 剩余经营收益 (ReOI) | C46: {=NOPAT-资本成本} -> #NAME? | E46: 【估值圣杯】<br>正数：创造价值（股价应高于净资产）。<br>负数：毁灭价值（股价应低于净资产）。<br>零：平庸公司。
A50: 共同比与趋势分析 (Common-Size & Trend)
B52: 毛利率：(营业收入-营业成本)/收入
B53: 销管费率 (SG&A %)：(销售费用+管理费用)/收入。看管理效率。
B54: 核心利润率：税前经营利润 / 收入。
B55: 存货占比：存货 / NOA。如果逐年上升，警惕滞销。
B56: 应收占比：应收账款 / NOA。如果逐年上升，警惕为了冲业绩放宽信用。

Sheet CF_Input
B1: 2024年年报 | C1: 2023年年报 | D1: 2022年年报 | E1: 2021年年报 | F1: 2020年年报 | G1: 2019年年报 | H1: 2018年年报 | I1: 2017年年报 | J1: 2016年年报
A2: 上市前/上市后 | B2: 上市后 | C2: 上市后 | D2: 上市后 | E2: 上市后 | F2: 上市后 | G2: 上市后 | H2: 上市前 | I2: 上市前 | J2: 上市前
A3: 报表类型 | B3: 合并报表 | C3: 合并报表 | D3: 合并报表 | E3: 合并报表 | F3: 合并报表 | G3: 合并报表 | H3: 合并报表 | I3: 合并报表 | J3: 合并报表
A4: 公司类型 | B4: 通用 | C4: 通用 | D4: 通用 | E4: 通用 | F4: 通用 | G4: 通用 | H4: 通用 | I4: 通用 | J4: 通用
A5: 经营活动产生的现金流量：
A6: 销售商品、提供劳务收到的现金(元) | B6: 4.1966277e+09 | C6: 4.0929026e+09 | D6: 4.4803122e+09 | E6: 3.4315348e+09 | F6: 2.7721684e+09 | G6: 2.7398032e+09 | H6: 2.2533811e+09 | I6: 1.5964024e+09 | J6: 1.3582774e+09
A7: 客户存款和同业存放款项净增加额(元)
A8: 向中央银行借款净增加额(元)
A9: 向其他金融机构拆入资金净增加额(元)
A10: 收到原保险合同保费取得的现金(元)
A11: 收到再保险业务现金净额(元)
A12: 保户储金及投资款净增加额(元)
A13: 处置交易性金融资产净增加额(元)
A14: 收取利息、手续费及佣金的现金(元)
A15: 拆入资金净增加额(元)
A16: 发放贷款及垫款的净减少额(元)
A17: 回购业务资金净增加额(元)
A18: 收到的税费返还(元) | B18: 13839887 | C18: 47653478 | D18: 80051944 | E18: 1879935.1 | H18: 24659840 | I18: 1686701.1
A19: 收到其他与经营活动有关的现金(元) | B19: 1.27481e+08 | C19: 89795638 | D19: 1.1307368e+08 | E19: 1.056754e+08 | F19: 55212251 | G19: 36604071 | H19: 27395796 | I19: 37623708 | J19: 30478425
A20: 经营活动现金流入的其他项目(元)
A21: 经营活动现金流入的平衡项目(元) | B21: 0 | C21: 0 | D21: 0 | E21: 0 | F21: 0 | G21: 0 | H21: 0 | I21: 0 | J21: 0
A22: 经营活动现金流入小计(元) | B22: 4.3379486e+09 | C22: 4.2303517e+09 | D22: 4.6734379e+09 | E22: 3.5390902e+09 | F22: 2.8273807e+09 | G22: 2.7764073e+09 | H22: 2.3054368e+09 | I22: 1.6357128e+09 | J22: 1.3887559e+09
A23: 购买商品、接受劳务支付的现金(元) | B23: 1.6159168e+09 | C23: 2.3592529e+09 | D23: 2.1795172e+09 | E23: 1.80731e+09 | F23: 1.2498336e+09 | G23: 1.3535816e+09 | H23: 1.1189247e+09 | I23: 8.6345813e+08 | J23: 4.8051585e+08
A24: 客户贷款及垫款净增加额(元)
A25: 存放中央银行和同业款项净增加额(元)
A26: 支付原保险合同赔付款项的现金(元)
A27: 支付利息、手续费及佣金的现金(元)
A28: 支付保单红利的现金(元)
A29: 支付给职工以及为职工支付的现金(元) | B29: 8.7644321e+08 | C29: 9.0634151e+08 | D29: 7.8767787e+08 | E29: 5.9530457e+08 | F29: 4.7895752e+08 | G29: 4.5393623e+08 | H29: 4.3643006e+08 | I29: 3.7669524e+08 | J29: 2.5316705e+08
A30: 支付的各项税费(元) | B30: 5.4995506e+08 | C30: 5.2041584e+08 | D30: 5.11427e+08 | E30: 3.9640093e+08 | F30: 3.608826e+08 | G30: 3.2868887e+08 | H30: 2.3536519e+08 | I30: 2.1423831e+08 | J30: 1.6874226e+08
A31: 支付其他与经营活动有关的现金(元) | B31: 2.551032e+08 | C31: 1.7631151e+08 | D31: 1.7199853e+08 | E31: 1.6299505e+08 | F31: 1.2676431e+08 | G31: 1.9630913e+08 | H31: 1.8780623e+08 | I31: 1.5137632e+08 | J31: 1.1949462e+08
A32: 经营活动现金流出的其他项目(元)
A33: 经营活动现金流出的平衡项目(元) | B33: 0 | C33: 0 | D33: 0 | E33: 0 | F33: 0 | G33: 0 | H33: 0 | I33: 0 | J33: 0
A34: 经营活动现金流出小计(元) | B34: 3.2974182e+09 | C34: 3.9623218e+09 | D34: 3.6506206e+09 | E34: 2.9620106e+09 | F34: 2.2164381e+09 | G34: 2.3325158e+09 | H34: 1.9785262e+09 | I34: 1.605768e+09 | J34: 1.0219198e+09
A35: 经营活动产生的现金流量净额其他项目(元)
A36: 经营活动产生的现金流量净额平衡项目(元) | B36: 0 | C36: 0 | D36: 0 | E36: 0 | F36: 0 | G36: 0 | H36: 0 | I36: 0 | J36: 0
A37: 经营活动产生的现金流量净额(元) | B37: 1.0405304e+09 | C37: 2.6802996e+08 | D37: 1.0228172e+09 | E37: 5.7707959e+08 | F37: 6.109426e+08 | G37: 4.4389151e+08 | H37: 3.269106e+08 | I37: 29944782 | J37: 3.6683609e+08
A38: 投资活动产生的现金流量：
A39: 收回投资收到的现金(元) | B39: 2604.16 | C39: 90997.62 | F39: 300000000 | G39: 10000000
A40: 取得投资收益收到的现金(元) | B40: 0 | F40: 9379761.5 | G40: 24630.14
A41: 处置固定资产、无形资产和其他长期资产收回的现金净额(元) | B41: 385754 | C41: 10809657 | D41: 1029291 | E41: 3669652 | F41: 4712046 | G41: 3673642 | H41: 1618790 | I41: 1383269 | J41: 1150000
A42: 处置子公司及其他营业单位收到的现金净额(元) | B42: 0 | C42: 317197.13
A43: 减少质押和定期存款所收到的现金(元)
A44: 收到的其他与投资活动有关的现金(元) | B44: 123590000 | C44: 61582313 | D44: 1.2562667e+08 | I44: 35000000
A45: 投资活动现金流入的其他项目(元)
A46: 投资活动现金流入的平衡项目(元) | B46: 0 | C46: 0 | D46: 0 | E46: 0 | F46: 0 | G46: 0 | H46: 0 | I46: 0 | J46: 0
A47: 投资活动现金流入小计(元) | B47: 1.2397836e+08 | C47: 72800164 | D47: 1.2665596e+08 | E47: 3669652 | F47: 3.1409181e+08 | G47: 13698272 | H47: 1618790 | I47: 36383269 | J47: 1150000
A48: 购建固定资产、无形资产和其他长期资产支付的现金(元) | B48: 1.9072846e+08 | C48: 1.1771097e+08 | D48: 2.9959146e+08 | E48: 1.9826536e+08 | F48: 1.0773943e+08 | G48: 11639205 | H48: 22934251 | I48: 62976073 | J48: 41809058
A49: 投资支付的现金(元) | B49: 0 | G49: 310000000
A50: 质押贷款净增加额(元)
A51: 取得子公司及其他营业单位支付的现金(元)
A52: 增加质押和定期存款所支付的现金(元)
A53: 支付其他与投资活动有关的现金(元) | B53: 175030000 | D53: 137412562 | E53: 1.3883445e+08 | I53: 35000000
A54: 投资活动现金流出的其他项目(元)
A55: 投资活动现金流出的平衡项目(元) | B55: 0 | C55: 0 | D55: 0 | E55: 0 | F55: 0 | G55: 0 | H55: 0 | I55: 0 | J55: 0
A56: 投资活动现金流出小计(元) | B56: 3.6575846e+08 | C56: 1.1771097e+08 | D56: 4.3700402e+08 | E56: 3.3709981e+08 | F56: 1.0773943e+08 | G56: 3.2163921e+08 | H56: 22934251 | I56: 97976073 | J56: 41809058
A57: 投资活动产生的现金流量净额其他项目(元)
A58: 投资活动产生的现金流量净额平衡项目(元) | B58: 0 | C58: 0 | D58: 0 | E58: 0 | F58: 0 | G58: 0 | H58: 0 | I58: 0 | J58: 0
A59: 投资活动产生的现金流量净额(元) | B59: -2.417801e+08 | C59: -44910807 | D59: -3.1034806e+08 | E59: -3.3343015e+08 | F59: 2.0635238e+08 | G59: -3.0794093e+08 | H59: -21315461 | I59: -61592804 | J59: -40659058
A60: 筹资活动产生的现金流量：
A61: 吸收投资收到的现金(元) | D61: 1.6312082e+08 | E61: 2238600 | F61: 124769970 | G61: 499262000
A62: 其中：子公司吸收少数股东投资收到的现金(元)
A63: 取得借款收到的现金(元) | B63: 470000000 | C63: 500000000 | D63: 49241667
A64: 发行债券收到的现金(元)
A65: 收到其他与筹资活动有关的现金(元) | B65: 3.878743e+08 | C65: 2.9910725e+08 | D65: 1.2312359e+08 | E65: 1.562274e+08 | F65: 45146300 | G65: 77328539 | H65: 39907384 | I65: 22371210 | J65: 24849730
A66: 筹资活动现金流入其他项目(元)
A67: 筹资活动现金流入平衡项目(元) | B67: 0 | C67: 0 | D67: 0 | E67: 0 | F67: 0 | G67: 0 | H67: 0 | I67: 0 | J67: 0
A68: 筹资活动现金流入小计(元) | B68: 8.578743e+08 | C68: 7.9910725e+08 | D68: 3.3548608e+08 | E68: 1.58466e+08 | F68: 1.6991627e+08 | G68: 5.7659054e+08 | H68: 39907384 | I68: 22371210 | J68: 24849730
A69: 偿还债务支付的现金(元) | B69: 380000000 | C69: 300000000 | J69: 3.592514e+08
A70: 分配股利、利润或偿付利息支付的现金(元) | B70: 9.9772231e+08 | C70: 5.8081601e+08 | D70: 329533200 | E70: 2.8591883e+08 | F70: 240021000 | G70: 240021000 | I70: 98055000 | J70: 5575887.4
A71: 其中：子公司支付给少数股东的股利、利润(元)
A72: 购买子公司少数股权而支付的现金(元)
A73: 支付其他与筹资活动有关的现金(元) | B73: 3.4523354e+08 | C73: 4.356812e+08 | D73: 2.9148733e+08 | E73: 3.3567585e+08 | F73: 53803744 | G73: 74676800 | H73: 45652860 | I73: 33688379 | J73: 35299937
A74: 其中：子公司减资支付给少数股东的现金(元)
A75: 筹资活动现金流出其他项目(元)
A76: 筹资活动现金流出平衡项目(元) | B76: 0 | C76: 0 | D76: 0 | E76: 0 | F76: 0 | G76: 0 | H76: 0 | I76: 0 | J76: 0
A77: 筹资活动现金流出小计(元) | B77: 1.7229558e+09 | C77: 1.3164972e+09 | D77: 6.2102053e+08 | E77: 6.2159469e+08 | F77: 2.9382474e+08 | G77: 3.146978e+08 | H77: 45652860 | I77: 1.3174338e+08 | J77: 4.0012722e+08
A78: 筹资活动产生的现金流量净额其他项目(元)
A79: 筹资活动产生的现金流量净额平衡项目(元) | B79: 0 | C79: 0 | D79: 0 | E79: 0 | F79: 0 | G79: 0 | H79: 0 | I79: 0 | J79: 0
A80: 筹资活动产生的现金流量净额(元) | B80: -8.6508155e+08 | C80: -5.1738997e+08 | D80: -2.8553445e+08 | E80: -4.6312869e+08 | F80: -1.2390847e+08 | G80: 2.6189274e+08 | H80: -5745476.5 | I80: -1.0937217e+08 | J80: -3.752775e+08
A81: 汇率变动对现金及现金等价物的影响(元) | B81: 54196.89 | C81: 2529778 | D81: 2855753.5 | E81: -2386748.3 | F81: -2400567.4 | G81: 1085114.2 | H81: 110034.78 | I81: -1407509.7 | J81: 1045808.8
A82: 现金及现金等价物净增加额其他项目(元)
A83: 现金及现金等价物净增加额平衡项目(元) | B83: 0 | C83: 0 | D83: 0 | E83: 0 | F83: 0 | G83: 0 | H83: 0 | I83: 0 | J83: 0
A84: 现金及现金等价物净增加额(元) | B84: -66277077 | C84: -2.9174103e+08 | D84: 429790488 | E84: -2.21866e+08 | F84: 6.9098594e+08 | G84: 3.9892843e+08 | H84: 2.999597e+08 | I84: -1.424277e+08 | J84: -48054656
A85: 期初现金及现金等价物余额(元) | B85: 1.5130165e+09 | C85: 1.8047575e+09 | D85: 1.374967e+09 | E85: 1.596833e+09 | F85: 9.058471e+08 | G85: 5.0691868e+08 | H85: 2.0695898e+08 | I85: 3.4938668e+08 | J85: 3.9744134e+08
A86: 期末现金及现金等价物余额其他项目(元)
A87: 期末现金及现金等价物余额平衡项目(元) | B87: 0 | C87: 0 | D87: 0 | E87: 0 | F87: 0 | G87: 0 | H87: 0 | I87: 0 | J87: 0
A88: 期末现金及现金等价物余额(元) | B88: 1.4467394e+09 | C88: 1.5130165e+09 | D88: 1.8047575e+09 | E88: 1.374967e+09 | F88: 1.596833e+09 | G88: 9.058471e+08 | H88: 5.0691868e+08 | I88: 2.0695898e+08 | J88: 3.4938668e+08
A89: 补充资料：
A90: 净利润(元) | B90: 8.4823119e+08 | C90: 1.0080895e+09 | D90: 8.3391867e+08 | E90: 6.4700609e+08 | F90: 5.1468257e+08 | G90: 4.1307695e+08 | H90: 244475700 | I90: 205956700 | J90: 159745000
A91: 资产减值准备(元) | B91: 10215468 | C91: 20696202 | D91: 11634694 | E91: 22210680 | F91: 15172795 | G91: 17301574 | H91: 15336400 | I91: -4686200 | J91: 29608700
A92: 信用减值损失(元) | B92: 39397334 | C92: -231206.7 | D92: 22572029 | E92: -5166307.5 | F92: 8664672.2
A93: 固定资产和投资性房地产折旧(元) | B93: 2.0346567e+08 | C93: 1.6392548e+08 | D93: 1.225338e+08 | E93: 98879455 | F93: 93026155 | G93: 90328530 | H93: 82564000 | I93: 73486400 | J93: 69416500
A94: 其中：固定资产折旧、油气资产折耗、生产性生物资产折旧(元) | B94: 2.0346567e+08 | C94: 1.6392548e+08 | D94: 1.225338e+08 | E94: 98879455 | F94: 93026155 | G94: 90328530 | H94: 82564000 | I94: 73486400 | J94: 69416500
A95: 投资性房地产折旧(元)
A96: 无形资产摊销(元) | B96: 9028406.8 | C96: 8352233.1 | D96: 7779373.1 | E96: 6339689 | F96: 6090420 | G96: 5390879.7 | H96: 5340800 | I96: 5341700 | J96: 5419000
A97: 长期待摊费用摊销(元)
A98: 递延收益摊销(元)
A99: 待摊费用的减少(元)
A100: 预提费用的增加(元)
...

Sheet 所有者权益变动表重构
A1: 行号 | B1: A (项目) | C1: B (金额/填入你的数据) | D1: C (逻辑与公式)
A2: 1 | B2: 一、期初存量
A3: 2 | B3: 期初归属于母公司所有者权益 | C3: 4.4640892e+09 | D3: 直接抄报表期初数
A4: 3 | B4: (+) 期初应付股利 | C4: 0 | D4: 若资产负债表有余额则填入，否则为0
A5: 4 | B5: 重构期初普通股权益 (A) | C5: =C3+C4 -> 4.4640892e+09 | D5: 这是你的起点
A7: 5 | B7: 二、流量：重构综合收益 | D7: 公司真正赚的钱
A8: 6 | B8: 综合收益总额 (净利润+OCI) | C8: 3.2794808e+08 | D8: 抄报表“综合收益总额”行
A9: 7 | B9: (-) 专项储备本期使用 | C9: 676339.94 | D9: 抄报表“专项储备-本期使用”，填正数，公式里减
A10: 8 | B10: (-) 优先股股利 | C10: 0 | D10: 若有则填，无则为0
A11: 9 | B11: 重构综合收益合计 (B) | C11: =C8-C9-C10 -> 3.2727174e+08 | D11: 注意：专项储备使用视为费用消耗
A13: 10 | B13: 三、流量：对股东净支付 | D13: 股东拿走(正) vs 股东投入(负)
A14: 11 | B14: (+) 现金分红 | C14: 230582800 | D14: 抄报表“对所有者分配”绝对值
A15: 12 | B15: (+) 股票回购 (库存股增加) | C15: 0 | D15: 若“库存股”列为正数(回购)，填在这里
A16: 13 | B16: (-) 股票再发行 (库存股减少) | C16: 49207177 | D16: 若“库存股”列为负数，取绝对值填在这里
A17: 14 | B17: (-) 其他新股发行 (资本公积增加) | C17: 3470597.8 | D17: 抄“所有者投入普通股”行的资本公积增加额
A18: 15 | B18: (+/-) 应付股利变动 | C18: 0 | D18: 期末应付 - 期初应付 (通常为0)
A19: 16 | B19: 对股东净支付合计 (C) | C19: =C14+C15-C16-C17-C18 -> 1.7790503e+08 | D19: 正数代表净流出，负数代表净融资
A21: 17 | B21: 四、验证与勾稽
A22: 18 | B22: 计算得出的期末权益 | C22: =C5+C11-C19 -> 4.6134559e+09 | D22: 公式：期初 + 收益 - 净支付
A23: 19 | B23: 报表实际期末权益 | C23: 4.6134559e+09 | D23: 抄报表期末数，用于对比
A24: 20 | B24: 差额 (必须为0) | C24: =C22-C23 -> 0 | D24: 如果不是0，说明填错了
A36: 比率分析
A39: 行号 | B39: A (项目) | C39: B (计算公式/数据源) | D39: C (结果示例) | E39: D (逻辑说明)
A40: 21 | B40: 五、核心输入数据 (来自上表)
A41: 22 | B41: 期初重构权益 | C41: =C3+C4 -> 4.4640892e+09 | D41: 4464089226· | E41: 引用上表
A42: 23 | B42: 期末重构权益 | C42: =C23 -> 4.6134559e+09 | D42: 4613455938 | E42: 引用上表
A43: 24 | B43: 重构综合收益 | C43: =C11 -> 3.2727174e+08 | D43: 327271737 | E43: 引用上表
A44: 25 | B44: 对股东净支付 (Net Payout) | C44: =C19 -> 1.7790503e+08 | D44: 177905025 | E44: 正数=流出，负数=投入
A45: 26 | B45: 平均重构权益 | C45: =AVERAGE(C41:C42) -> 4.5387726e+09 | D45: 4538772582 | E45: 用于计算ROCE分母
A47: 27 | B47: 六、分红与留存比率 | E47: 看老板大不大方
A48: 28 | B48: 总发放率 (Total Payout Ratio) | C48: =(C14+C15)/C43 -> 0.70456069 | D48: （股利+股份回购金额）/综合收益 | E48: 每赚100块，分给股东54块
A49: 29 | B49: 收益留存率 (Retention Ratio) | C49: =1-C48 -> 0.29543931 | D49: 1-总发放率 | E49: 每赚100块，留46块发展
B50: 总发放额占权益比 | C50: =(C14+C15)/(C14+C15+C3) -> 0.049115849 | D50: （股利+股份回购）/(普通股东权益账面价值+股利+股份回购）
A52: 30 | B52: 七、盈利能力比率 | E52: 看赚钱效率
A53: 31 | B53: ROCE(半年报数据） | C53: =C43/C45 -> 0.07210578 | D53: 0.0721 | E53: 基于平均权益的收益率
A54: 32 | B54: ROCE (年化估计) | C54: =C53*2 -> 0.14421156 | D54: 0.1442 | E54: 简单乘以2，估算全年水平
A56: 33 | B56: 八、增长率分解 | E56: 看增长动力
A57: 34 | B57: 总权益增长率 | C57: =(C42-C41)/C41 -> 0.033459616 | D57: (期末重构权益-期初重构权益)/期初重构权益 | E57: 净资产这半年总共涨了多少
A58: 35 | B58: 分解1：内生增长 (ROCE期初) | C58: =C43/C41 -> 0.073312096 | D58: 重构综合收益/期初重构收益 | E58: 靠本事赚来的增长 (收益/期初)
A59: 36 | B59: 分解2：新增投资率 | C59: =-C44/C41 -> -0.03985248 | D59: “-对股东净支付/期初重构收益 | E59: 注意加负号！这是股东抽血导致的收缩
A60: 37 | B60: 验证 (必须相等) | C60: =C58+C59 -> 0.033459616 | D60: 内生增长 (ROCE期初)+新增投资率=总权益增长率 | E60: 内生(7.33%) - 抽血(3.99%) = 实际增长
